meshviewer/__init__.py
meshviewer/__main__.py
meshviewer/arcball_camera.py
meshviewer/camera.py
meshviewer/obj_loader.py
meshviewer/stl_loader.py
meshviewer/util.py
meshviewer/viewer.py
meshviewer/shaders/mesh.frag
meshviewer/shaders/mesh.vert
meshviewer-0.1.6.dist-info/licenses/LICENSE
tests/__init__.py
tests/test_basic.py
meshviewer-0.1.6.dist-info/METADATA
meshviewer-0.1.6.dist-info/WHEEL
meshviewer-0.1.6.dist-info/entry_points.txt
meshviewer-0.1.6.dist-info/top_level.txt
meshviewer-0.1.6.dist-info/RECORD
